setup_server.py
include/__init__.py
include/decorators.py
include/descriptors.py
include/errors.py
include/metaclasses.py
include/protocol.py
include/utils.py
include/variables.py
log_configs/__init__.py
log_configs/server_log_config.py
messenger_server_gb_Aikin.egg-info/PKG-INFO
messenger_server_gb_Aikin.egg-info/SOURCES.txt
messenger_server_gb_Aikin.egg-info/dependency_links.txt
messenger_server_gb_Aikin.egg-info/requires.txt
messenger_server_gb_Aikin.egg-info/top_level.txt
server/__init__.py
server/add_user.py
server/server_database.py
server/server_gui.py
server/server_main.py
unit_tests/__init__.py
unit_tests/test_client.py
unit_tests/test_server.py
unit_tests/test_utils.py