Metadata-Version: 1.0
Name: messenger-server-gb-Aikin
Version: 0.0.1
Summary: tutorial messenger server part GB by Aikin
Home-page: UNKNOWN
Author: Aikin Yakov
Author-email: wedel@list.ru
License: UNKNOWN
Platform: UNKNOWN
